Fin/__init__.py
Fin/__main__.py
102203584-1.0.0.dist-info/LICENSE
102203584-1.0.0.dist-info/METADATA
102203584-1.0.0.dist-info/WHEEL
102203584-1.0.0.dist-info/entry_points.txt
102203584-1.0.0.dist-info/top_level.txt
102203584-1.0.0.dist-info/RECORD
